<?xml version="1.0" encoding="UTF-8"?>
<objects serializationModel="Studio.02.02.00">
	<object class="AudioFile" id="{33dae478-3ad4-48b9-ba4a-866145de46b6}">
		<property name="assetPath">
			<value>Max SFX/SDVG05S_office_scatter_01.wav</value>
		</property>
		<property name="frequencyInKHz">
			<value>48</value>
		</property>
		<property name="channelCount">
			<value>1</value>
		</property>
		<property name="length">
			<value>5.2196249999999997</value>
		</property>
		<relationship name="masterAssetFolder">
			<destination>{39f5cb70-36f3-4695-a94f-568a76a7769a}</destination>
		</relationship>
	</object>
</objects>
